torbox_api/__init__.py
torbox_api/sdk.py
torbox_api/sdk_async.py
torbox_api/hooks/__init__.py
torbox_api/hooks/hook.py
torbox_api/models/__init__.py
torbox_api/models/add_referral_to_account_ok_response.py
torbox_api/models/control_torrent_ok_response.py
torbox_api/models/create_torrent_ok_response.py
torbox_api/models/create_torrent_request.py
torbox_api/models/create_usenet_download_ok_response.py
torbox_api/models/create_usenet_download_request.py
torbox_api/models/create_web_download_ok_response.py
torbox_api/models/create_web_download_request.py
torbox_api/models/export_torrent_data_ok_response.py
torbox_api/models/get_all_jobs_by_hash_ok_response.py
torbox_api/models/get_all_jobs_ok_response.py
torbox_api/models/get_changelogs_json_ok_response.py
torbox_api/models/get_hoster_list_ok_response.py
torbox_api/models/get_notification_feed_ok_response.py
torbox_api/models/get_stats_ok_response.py
torbox_api/models/get_torrent_cached_availability_ok_response.py
torbox_api/models/get_torrent_info1_ok_response.py
torbox_api/models/get_torrent_info1_request.py
torbox_api/models/get_torrent_info_ok_response.py
torbox_api/models/get_torrent_list_ok_response.py
torbox_api/models/get_up_status_ok_response.py
torbox_api/models/get_usenet_list_ok_response.py
torbox_api/models/get_user_data_ok_response.py
torbox_api/models/get_web_download_list_ok_response.py
torbox_api/models/request_download_link_ok_response.py
torbox_api/models/utils/__init__.py
torbox_api/models/utils/base_model.py
torbox_api/models/utils/cast_models.py
torbox_api/models/utils/json_map.py
torbox_api/models/utils/one_of_base_model.py
torbox_api/models/utils/sentinel.py
torbox_api/net/__init__.py
torbox_api/net/environment/__init__.py
torbox_api/net/environment/environment.py
torbox_api/net/headers/__init__.py
torbox_api/net/headers/access_token_auth.py
torbox_api/net/headers/base_header.py
torbox_api/net/request_chain/__init__.py
torbox_api/net/request_chain/request_chain.py
torbox_api-1.0.6.dist-info/licenses/LICENSE
torbox_api-1.0.6.dist-info/METADATA
torbox_api-1.0.6.dist-info/WHEEL
torbox_api-1.0.6.dist-info/top_level.txt
torbox_api-1.0.6.dist-info/RECORD
