Metadata-Version: 2.4
Name: torbox-api
Version: 1.0.6
Summary: You can view the full documentation at https://api-docs.torbox.app.
License: MIT
Requires-Python: >=3.7
License-File: LICENSE
Requires-Dist: requests>=2.31.0
Dynamic: license-file
